sem6/DAV.py
sem6/ML-1.py
sem6/ML-10.py
sem6/ML-2.py
sem6/ML-3.py
sem6/ML-4.py
sem6/ML-5.py
sem6/ML-7.py
sem6/ML-8.py
sem6/ML-9.py
sem6/__init__.py
sem6/programs.py
DMCE_AIDS-0.0.6.dist-info/METADATA
DMCE_AIDS-0.0.6.dist-info/WHEEL
DMCE_AIDS-0.0.6.dist-info/entry_points.txt
DMCE_AIDS-0.0.6.dist-info/top_level.txt
DMCE_AIDS-0.0.6.dist-info/RECORD
